Metadata-Version: 2.1
Name: affinity-crm
Version: 1.0.2
Summary: Affinity CRM
Home-page: https://github.com/natefduncan/affinity
Author: Nathan Duncan
Author-email: natefduncan@gmail.com
License: UNKNOWN
Platform: UNKNOWN
License-File: LICENSE
